dalpha_ai/__init__.py
dalpha_ai/core/__init__.py
dalpha_ai/core/losses.py
dalpha_ai/core/classifier/__init__.py
dalpha_ai/core/classifier/base_classifier.py
dalpha_ai/core/classifier/base_config.py
dalpha_ai/core/classifier/base_datamodule.py
dalpha_ai/core/classifier/base_feedback_trainer.py
dalpha_ai/core/classifier/base_trainer.py
dalpha_ai/core/classifier/custom_ops.py
dalpha_ai/core/classifier/head_classifier.py
dalpha_ai/core/classifier/trainer_util.py
dalpha_ai/core/classifier/image_classifier/__init__.py
dalpha_ai/core/classifier/image_classifier/image_classifier.py
dalpha_ai/core/classifier/image_classifier/image_config.py
dalpha_ai/core/classifier/image_classifier/image_datamodule.py
dalpha_ai/core/classifier/image_classifier/image_trainer.py
dalpha_ai/core/classifier/image_text_classifier/__init__.py
dalpha_ai/core/classifier/image_text_classifier/image_text_classifier.py
dalpha_ai/core/classifier/image_text_classifier/image_text_config.py
dalpha_ai/core/classifier/image_text_classifier/image_text_datamodule.py
dalpha_ai/core/classifier/image_text_classifier/image_text_trainer.py
dalpha_ai/core/classifier/text_classifier/__init__.py
dalpha_ai/core/classifier/text_classifier/text_classifier.py
dalpha_ai/core/classifier/text_classifier/text_config.py
dalpha_ai/core/classifier/text_classifier/text_datamodule.py
dalpha_ai/core/classifier/text_classifier/text_trainer.py
dalpha_ai/core/classifier/zeroshot_classifier/__init__.py
dalpha_ai/core/classifier/zeroshot_classifier/zeroshot_image_classifier.py
dalpha_ai/core/classifier/zeroshot_classifier/zeroshot_image_config.py
dalpha_ai/core/classifier/zeroshot_classifier/zeroshot_image_datamodule.py
dalpha_ai/core/pipeline/__init__.py
dalpha_ai/core/pipeline/onnx_pipeline.py
dalpha_ai/core/pipeline/onnx_util.py
dalpha_ai/core/pipeline/pytorch_pipeline.py
dalpha_ai/core/pipeline/util.py
dalpha_ai-0.3.5.dist-info/METADATA
dalpha_ai-0.3.5.dist-info/WHEEL
dalpha_ai-0.3.5.dist-info/top_level.txt
dalpha_ai-0.3.5.dist-info/RECORD
