Metadata-Version: 2.1
Name: dalpha-ai
Version: 0.3.5
Summary: UNKNOWN
Home-page: UNKNOWN
Author: UNKNOWN
Author-email: UNKNOWN
License: UNKNOWN
Platform: UNKNOWN
Requires-Dist: Pillow (==10.2.0)
Requires-Dist: Requests (==2.31.0)
Requires-Dist: easydict (==1.11)
Requires-Dist: numpy (<2.0)
Requires-Dist: onnxruntime-gpu (==1.16.3)
Requires-Dist: onnxscript (==0.1.0.dev20240107)
Requires-Dist: optimum (==1.10.1)
Requires-Dist: optimum-intel (==1.10.1)
Requires-Dist: pandas (==2.0.3)
Requires-Dist: peft (==0.7.1)
Requires-Dist: pytorch-lightning (==2.1.3)
Requires-Dist: timm (==0.9.12)
Requires-Dist: tqdm (==4.66.1)
Requires-Dist: transformers (==4.36.2)
